pygamess/__init__.py
pygamess/__main__.py
pygamess/email.py
pygamess/gamess.py
pygamess/gamout_parser.py
pygamess/pygamess_utils.py
pygamess/utils.py
pygamess-0.6.3.dist-info/METADATA
pygamess-0.6.3.dist-info/WHEEL
pygamess-0.6.3.dist-info/top_level.txt
pygamess-0.6.3.dist-info/RECORD
