Metadata-Version: 2.1
Name: pygamess
Version: 0.6.3
Summary: GAMESS wrapper for Python
Home-page: https://github.com/kzfm/pygamess
Author: Ohkawa Kazufumi
Author-email: kerolinq@gmail.com
License: MIT
Keywords: chemistry
Platform: UNKNOWN
Classifier: License :: OSI Approved :: MIT License
Classifier: Topic :: Scientific/Engineering :: Chemistry
Classifier: Development Status :: 2 - Pre-Alpha
Classifier: Operating System :: MacOS :: MacOS X
Classifier: Operating System :: POSIX
Classifier: Programming Language :: Python
Requires: rdkit
Requires: ruamel.YAML
